{
    "1531648": {
        "id": 1531648,
        "name": "Street Fighter 6",
        "isOnline": false,
        "state": "CREATED",
        "numEntrants": 5,
        "videogame": {
            "id": 43868
        },
        "startAt": 1771700400,
        "phaseGroups": [
            {
                "id": 3155312,
                "phase": {
                    "id": 2167902,
                    "name": "Bracket"
                },
                "progressionsOut": null
            }
        ],
        "tournament": "Arena Ultra Arcade 2026 #3",
        "tournament_id": 866337,
        "city": "Cora\u00e7\u00e3o Eucar\u00edstico",
        "url": "https://start.gg/tournament/arena-ultra-arcade-2026-3/event/street-fighter-6",
        "streams": null,
        "timezone": "America/Sao_Paulo",
        "tournament_startAt": 1771689600,
        "tournament_endAt": 1771711200,
        "tournament_registrationClosesAt": 1771693200,
        "images": [
            {
                "id": "9004645",
                "url": "https://images.start.gg/images/tournament/866337/image-9db9cb0f0a37728d4391fa8dce64407a.png",
                "type": "profile"
            },
            {
                "id": "9004647",
                "url": "https://images.start.gg/images/tournament/866337/image-b74601910baa4b1c487ba80252c8f5a9.png",
                "type": "banner"
            }
        ],
        "tournament_multievent": false,
        "tournament_venueName": null,
        "tournament_venueAddress": "R. Dom Jos\u00e9 Gaspar, 701 - Cora\u00e7\u00e3o Eucar\u00edstico, Belo Horizonte - MG, 30535-610, Brasil",
        "tournament_addrState": "MG",
        "tweet_id": "2007595586711671267"
    },
    "1528314": {
        "id": 1528314,
        "name": "Street Fighter 6 - Gold Tier",
        "isOnline": false,
        "state": "CREATED",
        "numEntrants": 1,
        "videogame": {
            "id": 43868
        },
        "startAt": 1774094400,
        "phaseGroups": [],
        "tournament": "FGCL - Fighting Game Championship Legend",
        "tournament_id": 864740,
        "city": "Engenho de Dentro",
        "url": "https://start.gg/tournament/fgcl-fighting-game-championship-legend/event/street-fighter-6-gold-tier",
        "streams": [
            {
                "streamName": "nebulafgc2"
            },
            {
                "streamName": "FR_7"
            },
            {
                "streamName": "nebulafgc"
            },
            {
                "streamName": "rBeowulfz"
            }
        ],
        "timezone": "America/Sao_Paulo",
        "tournament_startAt": 1774094400,
        "tournament_endAt": 1774119600,
        "tournament_registrationClosesAt": 1773450000,
        "images": [
            {
                "id": "9009000",
                "url": "https://images.start.gg/images/tournament/864740/image-a9808012596cc97277a2d0b0d28f9693.jpg",
                "type": "profile"
            },
            {
                "id": "9009201",
                "url": "https://images.start.gg/images/tournament/864740/image-00991dca6ebe93b876042d9eb515c856.jpg",
                "type": "banner"
            }
        ],
        "tournament_multievent": false,
        "tournament_venueName": null,
        "tournament_venueAddress": "R. Arquias Cordeiro, 1516 - Engenho de Dentro, Rio de Janeiro - RJ, 20770-001, Brasil",
        "tournament_addrState": "RJ",
        "tweet_id": "2008750808095948843"
    },
    "1307806": {
        "id": 1307806,
        "name": "Street Fighter 6 - PC",
        "isOnline": false,
        "state": "CREATED",
        "numEntrants": null,
        "videogame": {
            "id": 43868
        },
        "startAt": 1773489600,
        "phaseGroups": [
            {
                "id": 2768806,
                "phase": {
                    "id": 1880859,
                    "name": "Bracket"
                },
                "progressionsOut": null
            }
        ],
        "tournament": "FERVO 2026",
        "tournament_id": 754958,
        "city": "Liberdade",
        "url": "https://start.gg/tournament/fervo-2026/event/street-fighter-6-pc",
        "streams": null,
        "timezone": "America/Sao_Paulo",
        "tournament_startAt": 1773489600,
        "tournament_endAt": 1773626400,
        "tournament_registrationClosesAt": 1772985540,
        "images": [
            {
                "id": "7837691",
                "url": "https://images.start.gg/images/tournament/754958/image-8522483e94194ebd10d676d09f8e6169.png?ehk=D37dSKXJt69BDvXpRHK1yAs8jA5EUZlWdOSb7isqPZo%3D&ehkOptimized=PmQ4KgZZSHFj2JLZAtlbq394xr%2FscPyp3ee3RigpH%2Bo%3D",
                "type": "profile"
            },
            {
                "id": "9041296",
                "url": "https://images.start.gg/images/tournament/754958/image-c5a7c80f9cf841828e860e51e053da50.jpg",
                "type": "banner"
            }
        ],
        "tournament_multievent": false,
        "tournament_venueName": null,
        "tournament_venueAddress": "R. Gualaxo, 285 - Liberdade, S\u00e3o Paulo - SP, 01533-020, Brasil",
        "tournament_addrState": "SP",
        "tweet_id": "2013764284287742407"
    },
    "1560381": {
        "id": 1560381,
        "name": "BR Kumite - Street Fighter 6",
        "isOnline": true,
        "state": "ACTIVE",
        "numEntrants": 108,
        "videogame": {
            "id": 43868
        },
        "startAt": 1771455600,
        "phaseGroups": [
            {
                "id": 3202762,
                "state": 2,
                "phase": {
                    "name": "Pools"
                },
                "progressionsOut": [
                    {
                        "id": 13416636
                    },
                    {
                        "id": 13416638
                    },
                    {
                        "id": 13416640
                    },
                    {
                        "id": 13416642
                    },
                    {
                        "id": 13416644
                    },
                    {
                        "id": 13416646
                    },
                    {
                        "id": 13416648
                    },
                    {
                        "id": 13416650
                    }
                ],
                "standings": {
                    "pageInfo": {
                        "total": 54
                    },
                    "nodes": [
                        {
                            "placement": 9,
                            "entrant": {
                                "id": 22656768,
                                "name": "ZSF | mortalmiller",
                                "participants": [
                                    {
                                        "user": {
                                            "authorizations": [
                                                {
                                                    "externalUsername": "mortalmiller"
                                                }
                                            ]
                                        },
                                        "player": {
                                            "id": 1981118
                                        }
                                    }
                                ]
                            }
                        },
                        {
                            "placement": 9,
                            "entrant": {
                                "id": 22657423,
                                "name": "PHT | Malakabadoz",
                                "participants": [
                                    {
                                        "user": {
                                            "authorizations": [
                                                {
                                                    "externalUsername": "Malakabados"
                                                }
                                            ]
                                        },
                                        "player": {
                                            "id": 3376604
                                        }
                                    }
                                ]
                            }
                        },
                        {
                            "placement": 9,
                            "entrant": {
                                "id": 22663054,
                                "name": "theforce90",
                                "participants": [
                                    {
                                        "user": {
                                            "authorizations": [
                                                {
                                                    "externalUsername": "theforce90"
                                                }
                                            ]
                                        },
                                        "player": {
                                            "id": 2202474
                                        }
                                    }
                                ]
                            }
                        },
                        {
                            "placement": 17,
                            "entrant": {
                                "id": 22633586,
                                "name": "SilvaGames REV | DARK817",
                                "participants": [
                                    {
                                        "user": {
                                            "authorizations": [
                                                {
                                                    "externalUsername": "Diego_DARK_Lins"
                                                }
                                            ]
                                        },
                                        "player": {
                                            "id": 358693
                                        }
                                    }
                                ]
                            }
                        },
                        {
                            "placement": 17,
                            "entrant": {
                                "id": 22640664,
                                "name": "SamucaHG20",
                                "participants": [
                                    {
                                        "user": {
                                            "authorizations": [
                                                {
                                                    "externalUsername": "Hg20Samuca"
                                                }
                                            ]
                                        },
                                        "player": {
                                            "id": 2133111
                                        }
                                    }
                                ]
                            }
                        },
                        {
                            "placement": 17,
                            "entrant": {
                                "id": 22657385,
                                "name": "AbyssWalker",
                                "participants": [
                                    {
                                        "user": {
                                            "authorizations": null
                                        },
                                        "player": {
                                            "id": 4296079
                                        }
                                    }
                                ]
                            }
                        },
                        {
                            "placement": 17,
                            "entrant": {
                                "id": 22660102,
                                "name": "Lamen | bielnvd",
                                "participants": [
                                    {
                                        "user": {
                                            "authorizations": null
                                        },
                                        "player": {
                                            "id": 4793048
                                        }
                                    }
                                ]
                            }
                        },
                        {
                            "placement": 17,
                            "entrant": {
                                "id": 22660623,
                                "name": "VCL | carlin",
                                "participants": [
                                    {
                                        "user": {
                                            "authorizations": null
                                        },
                                        "player": {
                                            "id": 4771794
                                        }
                                    }
                                ]
                            }
                        },
                        {
                            "placement": 17,
                            "entrant": {
                                "id": 22661972,
                                "name": "PHT | vicg",
                                "participants": [
                                    {
                                        "user": {
                                            "authorizations": null
                                        },
                                        "player": {
                                            "id": 4256108
                                        }
                                    }
                                ]
                            }
                        },
                        {
                            "placement": 17,
                            "entrant": {
                                "id": 22662011,
                                "name": "-Zenith",
                                "participants": [
                                    {
                                        "user": {
                                            "authorizations": null
                                        },
                                        "player": {
                                            "id": 701233
                                        }
                                    }
                                ]
                            }
                        },
                        {
                            "placement": 17,
                            "entrant": {
                                "id": 22662096,
                                "name": "V\u00edtimas FC | Normaniaco",
                                "participants": [
                                    {
                                        "user": {
                                            "authorizations": [
                                                {
                                                    "externalUsername": "kono_Nio_da"
                                                }
                                            ]
                                        },
                                        "player": {
                                            "id": 4091744
                                        }
                                    }
                                ]
                            }
                        },
                        {
                            "placement": 17,
                            "entrant": {
                                "id": 22626842,
                                "name": "DXO | Bekitos",
                                "participants": [
                                    {
                                        "user": {
                                            "authorizations": [
                                                {
                                                    "externalUsername": "Bekitos_01"
                                                }
                                            ]
                                        },
                                        "player": {
                                            "id": 573918
                                        }
                                    }
                                ]
                            }
                        },
                        {
                            "placement": 17,
                            "entrant": {
                                "id": 22662063,
                                "name": "2G | Zangief_bolado",
                                "participants": [
                                    {
                                        "user": {
                                            "authorizations": [
                                                {
                                                    "externalUsername": "BoladoZangief"
                                                }
                                            ]
                                        },
                                        "player": {
                                            "id": 1408573
                                        }
                                    }
                                ]
                            }
                        },
                        {
                            "placement": 17,
                            "entrant": {
                                "id": 22642079,
                                "name": "NieL_",
                                "participants": [
                                    {
                                        "user": {
                                            "authorizations": [
                                                {
                                                    "externalUsername": "NieL_Messatsu"
                                                }
                                            ]
                                        },
                                        "player": {
                                            "id": 1279367
                                        }
                                    }
                                ]
                            }
                        },
                        {
                            "placement": 17,
                            "entrant": {
                                "id": 22649416,
                                "name": "OneBoy Player",
                                "participants": [
                                    {
                                        "user": {
                                            "authorizations": [
                                                {
                                                    "externalUsername": "OneBoy_BR"
                                                }
                                            ]
                                        },
                                        "player": {
                                            "id": 358695
                                        }
                                    }
                                ]
                            }
                        },
                        {
                            "placement": 17,
                            "entrant": {
                                "id": 22656958,
                                "name": "LucyForever",
                                "participants": [
                                    {
                                        "user": {
                                            "authorizations": null
                                        },
                                        "player": {
                                            "id": 3507976
                                        }
                                    }
                                ]
                            }
                        }
                    ]
                }
            },
            {
                "id": 3202763,
                "state": 2,
                "phase": {
                    "name": "Pools"
                },
                "progressionsOut": [
                    {
                        "id": 13416637
                    },
                    {
                        "id": 13416639
                    },
                    {
                        "id": 13416641
                    },
                    {
                        "id": 13416643
                    },
                    {
                        "id": 13416645
                    },
                    {
                        "id": 13416647
                    },
                    {
                        "id": 13416649
                    },
                    {
                        "id": 13416651
                    }
                ],
                "standings": {
                    "pageInfo": {
                        "total": 54
                    },
                    "nodes": [
                        {
                            "placement": 9,
                            "entrant": {
                                "id": 22658427,
                                "name": "Shodown | Jah_lexe",
                                "participants": [
                                    {
                                        "user": {
                                            "authorizations": [
                                                {
                                                    "externalUsername": "JahLexe"
                                                }
                                            ]
                                        },
                                        "player": {
                                            "id": 662584
                                        }
                                    }
                                ]
                            }
                        },
                        {
                            "placement": 9,
                            "entrant": {
                                "id": 22661875,
                                "name": "E1Sports | NotPedro",
                                "participants": [
                                    {
                                        "user": {
                                            "authorizations": [
                                                {
                                                    "externalUsername": "NotPedro3"
                                                }
                                            ]
                                        },
                                        "player": {
                                            "id": 2461262
                                        }
                                    }
                                ]
                            }
                        },
                        {
                            "placement": 9,
                            "entrant": {
                                "id": 22662425,
                                "name": "TomzinMilgrau",
                                "participants": [
                                    {
                                        "user": {
                                            "authorizations": null
                                        },
                                        "player": {
                                            "id": 4623114
                                        }
                                    }
                                ]
                            }
                        },
                        {
                            "placement": 9,
                            "entrant": {
                                "id": 22649396,
                                "name": "ZSF | Ferps",
                                "participants": [
                                    {
                                        "user": {
                                            "authorizations": [
                                                {
                                                    "externalUsername": "ferpsfgc"
                                                }
                                            ]
                                        },
                                        "player": {
                                            "id": 1685931
                                        }
                                    }
                                ]
                            }
                        },
                        {
                            "placement": 17,
                            "entrant": {
                                "id": 22650403,
                                "name": "ZSF | Caio cesar",
                                "participants": [
                                    {
                                        "user": {
                                            "authorizations": [
                                                {
                                                    "externalUsername": "caiocesarfgc"
                                                }
                                            ]
                                        },
                                        "player": {
                                            "id": 4877036
                                        }
                                    }
                                ]
                            }
                        },
                        {
                            "placement": 17,
                            "entrant": {
                                "id": 22659266,
                                "name": "Kaiji",
                                "participants": [
                                    {
                                        "user": {
                                            "authorizations": null
                                        },
                                        "player": {
                                            "id": 4715290
                                        }
                                    }
                                ]
                            }
                        },
                        {
                            "placement": 17,
                            "entrant": {
                                "id": 22659612,
                                "name": "NotleLinc",
                                "participants": [
                                    {
                                        "user": {
                                            "authorizations": [
                                                {
                                                    "externalUsername": "liinconl"
                                                }
                                            ]
                                        },
                                        "player": {
                                            "id": 3508567
                                        }
                                    }
                                ]
                            }
                        },
                        {
                            "placement": 17,
                            "entrant": {
                                "id": 22662090,
                                "name": "V\u00edtimas FC | Lynx",
                                "participants": [
                                    {
                                        "user": {
                                            "authorizations": [
                                                {
                                                    "externalUsername": "CinnamonLynx_"
                                                }
                                            ]
                                        },
                                        "player": {
                                            "id": 2531317
                                        }
                                    }
                                ]
                            }
                        },
                        {
                            "placement": 17,
                            "entrant": {
                                "id": 22662316,
                                "name": "NEXUS | | Gustta",
                                "participants": [
                                    {
                                        "user": {
                                            "authorizations": [
                                                {
                                                    "externalUsername": "GusttaHenry_"
                                                }
                                            ]
                                        },
                                        "player": {
                                            "id": 2242529
                                        }
                                    }
                                ]
                            }
                        },
                        {
                            "placement": 17,
                            "entrant": {
                                "id": 22662848,
                                "name": "DXO | Adept",
                                "participants": [
                                    {
                                        "user": {
                                            "authorizations": [
                                                {
                                                    "externalUsername": "AdeptFGC"
                                                }
                                            ]
                                        },
                                        "player": {
                                            "id": 1801886
                                        }
                                    }
                                ]
                            }
                        },
                        {
                            "placement": 17,
                            "entrant": {
                                "id": 22659365,
                                "name": "JPAT01",
                                "participants": [
                                    {
                                        "user": {
                                            "authorizations": null
                                        },
                                        "player": {
                                            "id": 1638126
                                        }
                                    }
                                ]
                            }
                        },
                        {
                            "placement": 17,
                            "entrant": {
                                "id": 22662522,
                                "name": "BLK | Mega",
                                "participants": [
                                    {
                                        "user": {
                                            "authorizations": [
                                                {
                                                    "externalUsername": "Blk_Mega"
                                                }
                                            ]
                                        },
                                        "player": {
                                            "id": 2251397
                                        }
                                    }
                                ]
                            }
                        },
                        {
                            "placement": 17,
                            "entrant": {
                                "id": 22662355,
                                "name": "Vitimas FC | Bersera",
                                "participants": [
                                    {
                                        "user": {
                                            "authorizations": [
                                                {
                                                    "externalUsername": "bersedorock"
                                                }
                                            ]
                                        },
                                        "player": {
                                            "id": 2842409
                                        }
                                    }
                                ]
                            }
                        },
                        {
                            "placement": 17,
                            "entrant": {
                                "id": 22662462,
                                "name": "Meija",
                                "participants": [
                                    {
                                        "user": {
                                            "authorizations": [
                                                {
                                                    "externalUsername": "SunMeija"
                                                }
                                            ]
                                        },
                                        "player": {
                                            "id": 2345736
                                        }
                                    }
                                ]
                            }
                        },
                        {
                            "placement": 17,
                            "entrant": {
                                "id": 22641020,
                                "name": "UBB | ElSakoGordo",
                                "participants": [
                                    {
                                        "user": {
                                            "authorizations": null
                                        },
                                        "player": {
                                            "id": 768806
                                        }
                                    }
                                ]
                            }
                        },
                        {
                            "placement": 25,
                            "entrant": {
                                "id": 22633984,
                                "name": "LF | Smokii",
                                "participants": [
                                    {
                                        "user": {
                                            "authorizations": [
                                                {
                                                    "externalUsername": "Smokii_FGC"
                                                }
                                            ]
                                        },
                                        "player": {
                                            "id": 3166481
                                        }
                                    }
                                ]
                            }
                        }
                    ]
                }
            },
            {
                "id": 3202764,
                "state": 1,
                "phase": {
                    "name": "TOP 8"
                },
                "progressionsOut": null,
                "standings": {
                    "pageInfo": {
                        "total": 108
                    },
                    "nodes": [
                        {
                            "placement": 17,
                            "entrant": {
                                "id": 22657423,
                                "name": "PHT | Malakabadoz",
                                "participants": [
                                    {
                                        "user": {
                                            "authorizations": [
                                                {
                                                    "externalUsername": "Malakabados"
                                                }
                                            ]
                                        },
                                        "player": {
                                            "id": 3376604,
                                            "gamerTag": "Malakabadoz"
                                        }
                                    }
                                ]
                            }
                        },
                        {
                            "placement": 17,
                            "entrant": {
                                "id": 22649396,
                                "name": "ZSF | Ferps",
                                "participants": [
                                    {
                                        "user": {
                                            "authorizations": [
                                                {
                                                    "externalUsername": "ferpsfgc"
                                                }
                                            ]
                                        },
                                        "player": {
                                            "id": 1685931,
                                            "gamerTag": "Ferps"
                                        }
                                    }
                                ]
                            }
                        },
                        {
                            "placement": 17,
                            "entrant": {
                                "id": 22661875,
                                "name": "E1Sports | NotPedro",
                                "participants": [
                                    {
                                        "user": {
                                            "authorizations": [
                                                {
                                                    "externalUsername": "NotPedro3"
                                                }
                                            ]
                                        },
                                        "player": {
                                            "id": 2461262,
                                            "gamerTag": "NotPedro"
                                        }
                                    }
                                ]
                            }
                        },
                        {
                            "placement": 17,
                            "entrant": {
                                "id": 22658427,
                                "name": "Shodown | Jah_lexe",
                                "participants": [
                                    {
                                        "user": {
                                            "authorizations": [
                                                {
                                                    "externalUsername": "JahLexe"
                                                }
                                            ]
                                        },
                                        "player": {
                                            "id": 662584,
                                            "gamerTag": "Jah_lexe"
                                        }
                                    }
                                ]
                            }
                        },
                        {
                            "placement": 17,
                            "entrant": {
                                "id": 22663054,
                                "name": "theforce90",
                                "participants": [
                                    {
                                        "user": {
                                            "authorizations": [
                                                {
                                                    "externalUsername": "theforce90"
                                                }
                                            ]
                                        },
                                        "player": {
                                            "id": 2202474,
                                            "gamerTag": "theforce90"
                                        }
                                    }
                                ]
                            }
                        },
                        {
                            "placement": 17,
                            "entrant": {
                                "id": 22656768,
                                "name": "ZSF | mortalmiller",
                                "participants": [
                                    {
                                        "user": {
                                            "authorizations": [
                                                {
                                                    "externalUsername": "mortalmiller"
                                                }
                                            ]
                                        },
                                        "player": {
                                            "id": 1981118,
                                            "gamerTag": "mortalmiller"
                                        }
                                    }
                                ]
                            }
                        },
                        {
                            "placement": 17,
                            "entrant": {
                                "id": 22662425,
                                "name": "TomzinMilgrau",
                                "participants": [
                                    {
                                        "user": {
                                            "authorizations": null
                                        },
                                        "player": {
                                            "id": 4623114,
                                            "gamerTag": "TomzinMilgrau"
                                        }
                                    }
                                ]
                            }
                        },
                        {
                            "placement": 33,
                            "entrant": {
                                "id": 22660102,
                                "name": "Lamen | bielnvd",
                                "participants": [
                                    {
                                        "user": {
                                            "authorizations": null
                                        },
                                        "player": {
                                            "id": 4793048,
                                            "gamerTag": "bielnvd"
                                        }
                                    }
                                ]
                            }
                        },
                        {
                            "placement": 33,
                            "entrant": {
                                "id": 22662011,
                                "name": "-Zenith",
                                "participants": [
                                    {
                                        "user": {
                                            "authorizations": null
                                        },
                                        "player": {
                                            "id": 701233,
                                            "gamerTag": "-Zenith"
                                        }
                                    }
                                ]
                            }
                        },
                        {
                            "placement": 33,
                            "entrant": {
                                "id": 22649416,
                                "name": "OneBoy Player",
                                "participants": [
                                    {
                                        "user": {
                                            "authorizations": [
                                                {
                                                    "externalUsername": "OneBoy_BR"
                                                }
                                            ]
                                        },
                                        "player": {
                                            "id": 358695,
                                            "gamerTag": "OneBoy Player"
                                        }
                                    }
                                ]
                            }
                        },
                        {
                            "placement": 33,
                            "entrant": {
                                "id": 22642079,
                                "name": "NieL_",
                                "participants": [
                                    {
                                        "user": {
                                            "authorizations": [
                                                {
                                                    "externalUsername": "NieL_Messatsu"
                                                }
                                            ]
                                        },
                                        "player": {
                                            "id": 1279367,
                                            "gamerTag": "NieL_"
                                        }
                                    }
                                ]
                            }
                        },
                        {
                            "placement": 33,
                            "entrant": {
                                "id": 22660623,
                                "name": "VCL | carlin",
                                "participants": [
                                    {
                                        "user": {
                                            "authorizations": null
                                        },
                                        "player": {
                                            "id": 4771794,
                                            "gamerTag": "carlin"
                                        }
                                    }
                                ]
                            }
                        },
                        {
                            "placement": 33,
                            "entrant": {
                                "id": 22640664,
                                "name": "SamucaHG20",
                                "participants": [
                                    {
                                        "user": {
                                            "authorizations": [
                                                {
                                                    "externalUsername": "Hg20Samuca"
                                                }
                                            ]
                                        },
                                        "player": {
                                            "id": 2133111,
                                            "gamerTag": "SamucaHG20"
                                        }
                                    }
                                ]
                            }
                        },
                        {
                            "placement": 33,
                            "entrant": {
                                "id": 22626842,
                                "name": "DXO | Bekitos",
                                "participants": [
                                    {
                                        "user": {
                                            "authorizations": [
                                                {
                                                    "externalUsername": "Bekitos_01"
                                                }
                                            ]
                                        },
                                        "player": {
                                            "id": 573918,
                                            "gamerTag": "Bekitos"
                                        }
                                    }
                                ]
                            }
                        },
                        {
                            "placement": 33,
                            "entrant": {
                                "id": 22662096,
                                "name": "V\u00edtimas FC | Normaniaco",
                                "participants": [
                                    {
                                        "user": {
                                            "authorizations": [
                                                {
                                                    "externalUsername": "kono_Nio_da"
                                                }
                                            ]
                                        },
                                        "player": {
                                            "id": 4091744,
                                            "gamerTag": "Normaniaco"
                                        }
                                    }
                                ]
                            }
                        },
                        {
                            "placement": 33,
                            "entrant": {
                                "id": 22661972,
                                "name": "PHT | vicg",
                                "participants": [
                                    {
                                        "user": {
                                            "authorizations": null
                                        },
                                        "player": {
                                            "id": 4256108,
                                            "gamerTag": "vicg"
                                        }
                                    }
                                ]
                            }
                        }
                    ]
                }
            },
            {
                "id": 3202765,
                "state": 1,
                "phase": {
                    "name": "Top 16"
                },
                "progressionsOut": [
                    {
                        "id": 13416652
                    },
                    {
                        "id": 13416653
                    },
                    {
                        "id": 13416654
                    },
                    {
                        "id": 13416655
                    },
                    {
                        "id": 13416656
                    },
                    {
                        "id": 13416657
                    },
                    {
                        "id": 13416658
                    },
                    {
                        "id": 13416659
                    }
                ],
                "standings": {
                    "pageInfo": {
                        "total": 16
                    },
                    "nodes": [
                        {
                            "placement": 1,
                            "entrant": null
                        },
                        {
                            "placement": 1,
                            "entrant": null
                        },
                        {
                            "placement": 1,
                            "entrant": null
                        },
                        {
                            "placement": 1,
                            "entrant": null
                        },
                        {
                            "placement": 1,
                            "entrant": null
                        },
                        {
                            "placement": 1,
                            "entrant": null
                        },
                        {
                            "placement": 1,
                            "entrant": null
                        },
                        {
                            "placement": 1,
                            "entrant": null
                        },
                        {
                            "placement": 1,
                            "entrant": null
                        },
                        {
                            "placement": 1,
                            "entrant": null
                        },
                        {
                            "placement": 1,
                            "entrant": null
                        },
                        {
                            "placement": 1,
                            "entrant": null
                        },
                        {
                            "placement": 1,
                            "entrant": null
                        },
                        {
                            "placement": 1,
                            "entrant": null
                        },
                        {
                            "placement": 1,
                            "entrant": null
                        },
                        {
                            "placement": 1,
                            "entrant": null
                        }
                    ]
                }
            }
        ],
        "tournament": "#54 BR Kumite Street Fighter 6",
        "tournament_id": 880872,
        "city": null,
        "url": "https://start.gg/tournament/54-br-kumite-street-fighter-6/event/br-kumite-street-fighter-6",
        "streams": [
            {
                "streamName": "ryoran"
            }
        ],
        "timezone": "America/Campo_Grande",
        "tournament_startAt": 1771455600,
        "tournament_endAt": 1771468200,
        "tournament_registrationClosesAt": 1771455000,
        "images": [
            {
                "id": "9142655",
                "url": "https://images.start.gg/images/tournament/880872/image-cba8d667d82e45b0c6e4cd4af1662842.png",
                "type": "profile"
            },
            {
                "id": "9142674",
                "url": "https://images.start.gg/images/tournament/880872/image-ef88c1999056926394603146982cee30.png",
                "type": "banner"
            }
        ],
        "tournament_multievent": false,
        "tournament_venueName": null,
        "tournament_venueAddress": "Brasil",
        "tournament_addrState": null,
        "tweet_id": "2022362899709149465",
        "postedRegistrationClosing": true,
        "postedPhaseResultIds": [],
        "postedStarting": true
    },
    "1545851": {
        "id": 1545851,
        "name": "Street Fighter 6",
        "isOnline": false,
        "state": "CREATED",
        "numEntrants": 3,
        "videogame": {
            "id": 43868
        },
        "startAt": 1782565200,
        "phaseGroups": [
            {
                "id": 3178525,
                "phase": {
                    "id": 2185725,
                    "name": "Pools"
                },
                "progressionsOut": [
                    {
                        "id": 13322600
                    },
                    {
                        "id": 13322604
                    },
                    {
                        "id": 13322608
                    },
                    {
                        "id": 13322612
                    },
                    {
                        "id": 13322616
                    },
                    {
                        "id": 13322620
                    }
                ]
            },
            {
                "id": 3178526,
                "phase": {
                    "id": 2185725,
                    "name": "Pools"
                },
                "progressionsOut": [
                    {
                        "id": 13322601
                    },
                    {
                        "id": 13322605
                    },
                    {
                        "id": 13322609
                    },
                    {
                        "id": 13322613
                    },
                    {
                        "id": 13322617
                    },
                    {
                        "id": 13322621
                    }
                ]
            },
            {
                "id": 3178527,
                "phase": {
                    "id": 2185725,
                    "name": "Pools"
                },
                "progressionsOut": [
                    {
                        "id": 13322602
                    },
                    {
                        "id": 13322606
                    },
                    {
                        "id": 13322610
                    },
                    {
                        "id": 13322614
                    },
                    {
                        "id": 13322618
                    },
                    {
                        "id": 13322622
                    }
                ]
            },
            {
                "id": 3178528,
                "phase": {
                    "id": 2185725,
                    "name": "Pools"
                },
                "progressionsOut": [
                    {
                        "id": 13322603
                    },
                    {
                        "id": 13322607
                    },
                    {
                        "id": 13322611
                    },
                    {
                        "id": 13322615
                    },
                    {
                        "id": 13322619
                    },
                    {
                        "id": 13322623
                    }
                ]
            },
            {
                "id": 3178529,
                "phase": {
                    "id": 2185726,
                    "name": "Top 24"
                },
                "progressionsOut": [
                    {
                        "id": 13322624
                    },
                    {
                        "id": 13322626
                    },
                    {
                        "id": 13322628
                    },
                    {
                        "id": 13322630
                    }
                ]
            },
            {
                "id": 3178530,
                "phase": {
                    "id": 2185726,
                    "name": "Top 24"
                },
                "progressionsOut": [
                    {
                        "id": 13322625
                    },
                    {
                        "id": 13322627
                    },
                    {
                        "id": 13322629
                    },
                    {
                        "id": 13322631
                    }
                ]
            },
            {
                "id": 3178531,
                "phase": {
                    "id": 2185727,
                    "name": "Top 8"
                },
                "progressionsOut": null
            }
        ],
        "tournament": "Chimarr\u00e3o Vs. 2026",
        "tournament_id": 873619,
        "city": "Petr\u00f3polis",
        "url": "https://start.gg/tournament/chimarr-o-vs-2026/event/street-fighter-6",
        "streams": [
            {
                "streamName": "smashrs_"
            },
            {
                "streamName": "ca_millia"
            }
        ],
        "timezone": "America/Sao_Paulo",
        "tournament_startAt": 1782565200,
        "tournament_endAt": 1782687600,
        "tournament_registrationClosesAt": 1782705540,
        "images": [
            {
                "id": "9141461",
                "url": "https://images.start.gg/images/tournament/873619/image-82ed23a15c5ca955a83e6469982e903d.png",
                "type": "profile"
            },
            {
                "id": "9141491",
                "url": "https://images.start.gg/images/tournament/873619/image-d2b25047aaf61c435a45afcc60c4351f.png",
                "type": "banner"
            }
        ],
        "tournament_multievent": false,
        "tournament_venueName": null,
        "tournament_venueAddress": "Av. Prot\u00e1sio Alves, 2966 - Petr\u00f3polis, Porto Alegre - RS, 90410-007, Brazil",
        "tournament_addrState": "RS",
        "tweet_id": "2022445934450274668"
    }
}