{
    "1116526": {
        "id": 1116526,
        "name": "XD 2, (ahora con plata)",
        "isOnline": false,
        "state": "CREATED",
        "numEntrants": 1,
        "videogame": {
            "id": 1386
        },
        "startAt": 1712748600,
        "phaseGroups": [
            {
                "id": 2437614,
                "phase": {
                    "id": 1633135,
                    "name": "Bracket"
                },
                "progressionsOut": null
            }
        ],
        "tournament": "Santo cura",
        "tournament_id": 657547,
        "city": "San Miguel",
        "url": "https://start.gg/tournament/santo-cura/event/xd-2-ahora-con-plata",
        "streams": null,
        "timezone": "America/Santiago",
        "tournament_startAt": 1712674200,
        "tournament_endAt": 1744257600,
        "tournament_registrationClosesAt": 1744257600,
        "images": [
            {
                "id": "6803811",
                "url": "https://images.start.gg/images/tournament/657547/image-94a6f96ace8350e287585fa9ff7ff3bf.jpg?ehk=74j%2B1pc9iQ4gtxU1A7D7p7DKfm1sYSbP%2BaUuipm7cX0%3D&ehkOptimized=oH4i6OAUCZtBtqijQRTg5UpX203nakhHxLh6Atus99U%3D",
                "type": "banner"
            },
            {
                "id": "6803825",
                "url": "https://images.start.gg/images/tournament/657547/image-de805cd1bcb7bc3c590d01beca5fb33f.jpg?ehk=Msbhx%2FI6y6GmEtK9to%2BjYba11bNNLsJoOiDEyKe9218%3D&ehkOptimized=l5NB6wAfW9%2B5pWd%2BvdCRo3F%2FlEYAXbm6QLE6DdYx4V8%3D",
                "type": "profile"
            }
        ],
        "tournament_multievent": true,
        "tournament_venueName": null,
        "tournament_venueAddress": "Carmen Mena 929, 8930180 San Miguel, Regi\u00f3n Metropolitana, Chile",
        "tournament_addrState": "Regi\u00f3n Metropolitana",
        "tweet_id": "1777811462255202539",
        "postedRegistrationClosing": true
    },
    "1209032": {
        "id": 1209032,
        "name": "Super Smash Bros Ultimate",
        "isOnline": false,
        "state": "CREATED",
        "numEntrants": null,
        "videogame": {
            "id": 1386
        },
        "startAt": 1728734400,
        "phaseGroups": [],
        "tournament": "FIGHT FOR GLORY",
        "tournament_id": 683530,
        "city": "Providencia",
        "url": "https://start.gg/tournament/fight-for-glory-1/event/super-smash-bros-ultimate",
        "streams": [
            {
                "streamName": "hadoukendojogamer"
            }
        ],
        "timezone": "America/Santiago",
        "tournament_startAt": 1728734400,
        "tournament_endAt": 1728835140,
        "tournament_registrationClosesAt": 1728529200,
        "images": [
            {
                "id": "7110959",
                "url": "https://images.start.gg/images/tournament/683530/image-2576cc881560a368a6a62ac16ae633cb.png?ehk=7dUl9ABpOSGIlFwH1vRc9d3kS2N%2FLxE9XQ8RG5i894I%3D&ehkOptimized=Evt5ktAofeXm0FtBqyEFEggYAPEst4W8DU2BajalexY%3D",
                "type": "profile"
            },
            {
                "id": "7161427",
                "url": "https://images.start.gg/images/tournament/683530/image-1146438fdc5c2041b0b0ffc66d0f55a8.jpg?ehk=8pIt5BVvSLAv9dDwKfz1sP2WhXgocz4yTIAV%2BF51BTI%3D&ehkOptimized=L4gsurh1Oo%2Fl%2BO1VHiIy1Fu6cjh67pKZXu%2F7HtkRgPQ%3D",
                "type": "banner"
            }
        ],
        "tournament_multievent": false,
        "tournament_venueName": null,
        "tournament_venueAddress": "Los Jesuitas 881, 7501300 Providencia, Regi\u00f3n Metropolitana, Chile",
        "tournament_addrState": "Regi\u00f3n Metropolitana",
        "tweet_id": "1831437333524091332",
        "retries": 8
    },
    "1217340": {
        "id": 1217340,
        "name": "MJC4 SINGLES",
        "isOnline": false,
        "state": "CREATED",
        "numEntrants": null,
        "videogame": {
            "id": 1386
        },
        "startAt": 1728151200,
        "phaseGroups": [
            {
                "id": 2616197,
                "phase": {
                    "id": 1764895,
                    "name": "Bracket"
                },
                "progressionsOut": null
            }
        ],
        "tournament": "El Mejor Cazador N\u00b04",
        "tournament_id": 710034,
        "city": "Vi\u00f1a del Mar",
        "url": "https://start.gg/tournament/el-mejor-cazador-n-4/event/mjc4-singles",
        "streams": null,
        "timezone": "America/Santiago",
        "tournament_startAt": 1728151200,
        "tournament_endAt": 1728176400,
        "tournament_registrationClosesAt": 1728172800,
        "images": [
            {
                "id": "7375620",
                "url": "https://images.start.gg/images/tournament/710034/image-90ee58598bfb5e992ae79f45ea2dcd0c.jpg?ehk=d0wS6jb%2FmyrUGWFc1pdXu1XGd3l09UlyQ8AGLDy%2Fel8%3D&ehkOptimized=rdpc6Eha6b5dS4v6C1p0fMVFspy4HjWqiXF1R01prK4%3D",
                "type": "profile"
            },
            {
                "id": "7375692",
                "url": "https://images.start.gg/images/tournament/710034/image-9590ee07c65f509ee3efc57672d0f078.jpg?ehk=8xDerZkvNJHxe26tnxQyzp3QdG5AGpRKf%2BF1%2Bc6zO1o%3D&ehkOptimized=4f0UcrdRTe%2F%2Ftlp1fb1jrEdQEylejG4f5funaKoU7tg%3D",
                "type": "banner"
            }
        ],
        "tournament_multievent": false,
        "tournament_venueName": null,
        "tournament_venueAddress": "Mar del Sur 74, Vi\u00f1a del Mar, Valpara\u00edso, Chile",
        "tournament_addrState": "Valpara\u00edso",
        "tweet_id": "1835778418614452569",
        "postedRegistrationClosing": true
    },
    "1218353": {
        "id": 1218353,
        "name": "Ultimate Dobles",
        "isOnline": false,
        "state": "CREATED",
        "numEntrants": 2,
        "videogame": {
            "id": 1386
        },
        "startAt": 1727542800,
        "phaseGroups": [
            {
                "id": 2617886,
                "phase": {
                    "id": 1766157,
                    "name": "Bracket"
                },
                "progressionsOut": null
            }
        ],
        "tournament": "Copa Civetana #4",
        "tournament_id": 710597,
        "city": "Providencia",
        "url": "https://start.gg/tournament/copa-civetana-4/event/ultimate-dobles",
        "streams": [
            {
                "streamName": "LevelZeroTeam"
            }
        ],
        "timezone": "America/Santiago",
        "tournament_startAt": 1727539200,
        "tournament_endAt": 1727564400,
        "tournament_registrationClosesAt": 1727542800,
        "images": [
            {
                "id": "7379898",
                "url": "https://images.start.gg/images/tournament/710597/image-a4b7fa683caa2d965e880953a1e2b10c.jpg?ehk=59CIIGQZMpdQUDpoP1XCKETOUOkor7%2BmjtIphg0vFO0%3D&ehkOptimized=tML3QCjsreniwBBeXphzviJzakkGC0FFlDlhBMnR1Ao%3D",
                "type": "profile"
            },
            {
                "id": "7379899",
                "url": "https://images.start.gg/images/tournament/710597/image-6c0ad03f7adeadd8a361dd62a9572398.jpg?ehk=Fi38gA2nwIidBRdXjE7L2ldB9MgnlKhcbwPUXyJBHtE%3D&ehkOptimized=i8ypDtDZ0NoLrTUQzc0dLapC%2BuPjK4148%2FryyA%2Bbv34%3D",
                "type": "banner"
            }
        ],
        "tournament_multievent": true,
        "tournament_venueName": null,
        "tournament_venueAddress": "Av. Vicu\u00f1a Mackenna 38, 7500907 Providencia, Regi\u00f3n Metropolitana, Chile",
        "tournament_addrState": "Regi\u00f3n Metropolitana",
        "tweet_id": "1836163450688401517",
        "postedRegistrationClosing": true
    },
    "1222380": {
        "id": 1222380,
        "name": "Singles Showdown",
        "isOnline": false,
        "state": "CREATED",
        "numEntrants": 10,
        "videogame": {
            "id": 1386
        },
        "startAt": 1728234000,
        "phaseGroups": [
            {
                "id": 2624735,
                "phase": {
                    "id": 1771337,
                    "name": "Bracket"
                },
                "progressionsOut": null
            }
        ],
        "tournament": "Start Showdown #7",
        "tournament_id": 712694,
        "city": "Puerto Montt",
        "url": "https://start.gg/tournament/start-showdown-7/event/singles-showdown",
        "streams": null,
        "timezone": "America/Santiago",
        "tournament_startAt": 1728234000,
        "tournament_endAt": 1728262800,
        "tournament_registrationClosesAt": 1728262800,
        "images": [
            {
                "id": "7402724",
                "url": "https://images.start.gg/images/tournament/712694/image-0329cb3f5bf4890844d15f9899b35f55.png?ehk=hj8YQ0Rn1e8cZFQPSREKCbi4NnJsDkIb3Ysi0g6S62c%3D&ehkOptimized=YxE2TrHRcOgWnpGYOnYEjRjWcipC%2FUBB8bb1WDShMo0%3D",
                "type": "profile"
            }
        ],
        "tournament_multievent": false,
        "tournament_venueName": null,
        "tournament_venueAddress": "Angelm\u00f3 2240, Puerto Montt, Los Lagos, Chile",
        "tournament_addrState": "Los Lagos",
        "tweet_id": "1838307678025560464"
    },
    "1223426": {
        "id": 1223426,
        "name": "Ultimate Singles Bracket",
        "isOnline": false,
        "state": "COMPLETED",
        "numEntrants": 13,
        "videogame": {
            "id": 1386
        },
        "startAt": 1727469000,
        "phaseGroups": [
            {
                "id": 2626346,
                "state": 3,
                "phase": {
                    "name": "Top 8"
                },
                "progressionsOut": null,
                "standings": {
                    "pageInfo": {
                        "total": 8
                    },
                    "nodes": [
                        {
                            "placement": 1,
                            "entrant": {
                                "id": 17940381,
                                "name": "PM | Tuxedo",
                                "participants": [
                                    {
                                        "user": {
                                            "authorizations": [
                                                {
                                                    "externalUsername": "Tuxedo_Smash"
                                                }
                                            ]
                                        },
                                        "player": {
                                            "id": 1137586
                                        }
                                    }
                                ]
                            }
                        },
                        {
                            "placement": 2,
                            "entrant": {
                                "id": 17944838,
                                "name": "Hb2",
                                "participants": [
                                    {
                                        "user": {
                                            "authorizations": [
                                                {
                                                    "externalUsername": "Pablo_Hb2"
                                                }
                                            ]
                                        },
                                        "player": {
                                            "id": 131600
                                        }
                                    }
                                ]
                            }
                        },
                        {
                            "placement": 3,
                            "entrant": {
                                "id": 17943300,
                                "name": "One way | Nekokatsu",
                                "participants": [
                                    {
                                        "user": {
                                            "authorizations": [
                                                {
                                                    "externalUsername": "MSSNekokatsu"
                                                }
                                            ]
                                        },
                                        "player": {
                                            "id": 530938
                                        }
                                    }
                                ]
                            }
                        },
                        {
                            "placement": 4,
                            "entrant": {
                                "id": 17940382,
                                "name": "PHX | Bear",
                                "participants": [
                                    {
                                        "user": {
                                            "authorizations": [
                                                {
                                                    "externalUsername": "bearded_bowser"
                                                }
                                            ]
                                        },
                                        "player": {
                                            "id": 409154
                                        }
                                    }
                                ]
                            }
                        },
                        {
                            "placement": 5,
                            "entrant": {
                                "id": 17943448,
                                "name": "ORD | KingSheikah",
                                "participants": [
                                    {
                                        "user": {
                                            "authorizations": null
                                        },
                                        "player": {
                                            "id": 895687
                                        }
                                    }
                                ]
                            }
                        },
                        {
                            "placement": 5,
                            "entrant": {
                                "id": 17944423,
                                "name": "Mttck",
                                "participants": [
                                    {
                                        "user": {
                                            "authorizations": null
                                        },
                                        "player": {
                                            "id": 1904161
                                        }
                                    }
                                ]
                            }
                        },
                        {
                            "placement": 7,
                            "entrant": {
                                "id": 17939159,
                                "name": "AC | Tind3us",
                                "participants": [
                                    {
                                        "user": {
                                            "authorizations": [
                                                {
                                                    "externalUsername": "tindeuszz"
                                                }
                                            ]
                                        },
                                        "player": {
                                            "id": 4114115
                                        }
                                    }
                                ]
                            }
                        },
                        {
                            "placement": 7,
                            "entrant": {
                                "id": 17944448,
                                "name": "UQS | Lopino",
                                "participants": [
                                    {
                                        "user": {
                                            "authorizations": [
                                                {
                                                    "externalUsername": "Lopino_"
                                                }
                                            ]
                                        },
                                        "player": {
                                            "id": 268946
                                        }
                                    }
                                ]
                            }
                        }
                    ]
                },
                "multiphase": true
            },
            {
                "id": 2626347,
                "state": 3,
                "phase": {
                    "name": "Singles"
                },
                "progressionsOut": [
                    {
                        "id": 11053844
                    },
                    {
                        "id": 11053845
                    },
                    {
                        "id": 11053846
                    },
                    {
                        "id": 11053847
                    },
                    {
                        "id": 11053848
                    },
                    {
                        "id": 11053849
                    },
                    {
                        "id": 11053850
                    },
                    {
                        "id": 11053851
                    },
                    {
                        "id": 11053852
                    },
                    {
                        "id": 11053853
                    },
                    {
                        "id": 11053854
                    },
                    {
                        "id": 11053855
                    },
                    {
                        "id": 11053856
                    },
                    {
                        "id": 11053857
                    },
                    {
                        "id": 11053858
                    },
                    {
                        "id": 11053859
                    }
                ],
                "standings": {
                    "pageInfo": {
                        "total": 13
                    },
                    "nodes": [
                        {
                            "placement": 5,
                            "entrant": {
                                "id": 17940381,
                                "name": "PM | Tuxedo",
                                "participants": [
                                    {
                                        "user": {
                                            "authorizations": [
                                                {
                                                    "externalUsername": "Tuxedo_Smash"
                                                }
                                            ]
                                        },
                                        "player": {
                                            "id": 1137586
                                        }
                                    }
                                ]
                            }
                        },
                        {
                            "placement": 5,
                            "entrant": {
                                "id": 17943300,
                                "name": "One way | Nekokatsu",
                                "participants": [
                                    {
                                        "user": {
                                            "authorizations": [
                                                {
                                                    "externalUsername": "MSSNekokatsu"
                                                }
                                            ]
                                        },
                                        "player": {
                                            "id": 530938
                                        }
                                    }
                                ]
                            }
                        },
                        {
                            "placement": 5,
                            "entrant": {
                                "id": 17943448,
                                "name": "ORD | KingSheikah",
                                "participants": [
                                    {
                                        "user": {
                                            "authorizations": null
                                        },
                                        "player": {
                                            "id": 895687
                                        }
                                    }
                                ]
                            }
                        },
                        {
                            "placement": 5,
                            "entrant": {
                                "id": 17944838,
                                "name": "Hb2",
                                "participants": [
                                    {
                                        "user": {
                                            "authorizations": [
                                                {
                                                    "externalUsername": "Pablo_Hb2"
                                                }
                                            ]
                                        },
                                        "player": {
                                            "id": 131600
                                        }
                                    }
                                ]
                            }
                        },
                        {
                            "placement": 7,
                            "entrant": {
                                "id": 17939159,
                                "name": "AC | Tind3us",
                                "participants": [
                                    {
                                        "user": {
                                            "authorizations": [
                                                {
                                                    "externalUsername": "tindeuszz"
                                                }
                                            ]
                                        },
                                        "player": {
                                            "id": 4114115
                                        }
                                    }
                                ]
                            }
                        },
                        {
                            "placement": 7,
                            "entrant": {
                                "id": 17940382,
                                "name": "PHX | Bear",
                                "participants": [
                                    {
                                        "user": {
                                            "authorizations": [
                                                {
                                                    "externalUsername": "bearded_bowser"
                                                }
                                            ]
                                        },
                                        "player": {
                                            "id": 409154
                                        }
                                    }
                                ]
                            }
                        },
                        {
                            "placement": 7,
                            "entrant": {
                                "id": 17944423,
                                "name": "Mttck",
                                "participants": [
                                    {
                                        "user": {
                                            "authorizations": null
                                        },
                                        "player": {
                                            "id": 1904161
                                        }
                                    }
                                ]
                            }
                        },
                        {
                            "placement": 7,
                            "entrant": {
                                "id": 17944448,
                                "name": "UQS | Lopino",
                                "participants": [
                                    {
                                        "user": {
                                            "authorizations": [
                                                {
                                                    "externalUsername": "Lopino_"
                                                }
                                            ]
                                        },
                                        "player": {
                                            "id": 268946
                                        }
                                    }
                                ]
                            }
                        },
                        {
                            "placement": 9,
                            "entrant": {
                                "id": 17920034,
                                "name": "PM | Gonzalo Tapia",
                                "participants": [
                                    {
                                        "user": {
                                            "authorizations": [
                                                {
                                                    "externalUsername": "POTO_SVRS"
                                                }
                                            ]
                                        },
                                        "player": {
                                            "id": 1237311
                                        }
                                    }
                                ]
                            }
                        },
                        {
                            "placement": 9,
                            "entrant": {
                                "id": 17921952,
                                "name": "Beleth",
                                "participants": [
                                    {
                                        "user": null,
                                        "player": {
                                            "id": 4337619
                                        }
                                    }
                                ]
                            }
                        },
                        {
                            "placement": 9,
                            "entrant": {
                                "id": 17940385,
                                "name": "Mu sin gen",
                                "participants": [
                                    {
                                        "user": null,
                                        "player": {
                                            "id": 4316624
                                        }
                                    }
                                ]
                            }
                        },
                        {
                            "placement": 9,
                            "entrant": {
                                "id": 17944280,
                                "name": "Louie",
                                "participants": [
                                    {
                                        "user": null,
                                        "player": {
                                            "id": 4340795
                                        }
                                    }
                                ]
                            }
                        },
                        {
                            "placement": 13,
                            "entrant": {
                                "id": 17943317,
                                "name": "disgod | DI$GOD",
                                "participants": [
                                    {
                                        "user": {
                                            "authorizations": null
                                        },
                                        "player": {
                                            "id": 3389692
                                        }
                                    }
                                ]
                            }
                        }
                    ]
                }
            },
            {
                "id": 2626348,
                "state": 3,
                "phase": {
                    "name": "SemiPro"
                },
                "progressionsOut": null,
                "standings": {
                    "pageInfo": {
                        "total": 8
                    },
                    "nodes": [
                        {
                            "placement": 1,
                            "entrant": {
                                "id": 17944280,
                                "name": "Louie",
                                "participants": [
                                    {
                                        "user": null,
                                        "player": {
                                            "id": 4340795
                                        }
                                    }
                                ]
                            }
                        },
                        {
                            "placement": 1,
                            "entrant": null
                        },
                        {
                            "placement": 1,
                            "entrant": null
                        },
                        {
                            "placement": 1,
                            "entrant": null
                        },
                        {
                            "placement": 2,
                            "entrant": {
                                "id": 17921952,
                                "name": "Beleth",
                                "participants": [
                                    {
                                        "user": null,
                                        "player": {
                                            "id": 4337619
                                        }
                                    }
                                ]
                            }
                        },
                        {
                            "placement": 3,
                            "entrant": {
                                "id": 17940385,
                                "name": "Mu sin gen",
                                "participants": [
                                    {
                                        "user": null,
                                        "player": {
                                            "id": 4316624
                                        }
                                    }
                                ]
                            }
                        },
                        {
                            "placement": 3,
                            "entrant": {
                                "id": 17920034,
                                "name": "PM | Gonzalo Tapia",
                                "participants": [
                                    {
                                        "user": {
                                            "authorizations": [
                                                {
                                                    "externalUsername": "POTO_SVRS"
                                                }
                                            ]
                                        },
                                        "player": {
                                            "id": 1237311
                                        }
                                    }
                                ]
                            }
                        },
                        {
                            "placement": 5,
                            "entrant": {
                                "id": 17943317,
                                "name": "disgod | DI$GOD",
                                "participants": [
                                    {
                                        "user": {
                                            "authorizations": null
                                        },
                                        "player": {
                                            "id": 3389692
                                        }
                                    }
                                ]
                            }
                        }
                    ]
                },
                "multiphase": true
            }
        ],
        "tournament": "Smash Bros \u00d1u\u00f1oa #61",
        "tournament_id": 713228,
        "city": "Santiago",
        "url": "https://start.gg/tournament/smash-bros-u-oa-61/event/ultimate-singles-bracket",
        "streams": [
            {
                "streamName": "oneway_esports"
            }
        ],
        "timezone": "America/Santiago",
        "tournament_startAt": 1727469000,
        "tournament_endAt": 1727485200,
        "tournament_registrationClosesAt": 1727476200,
        "images": [
            {
                "id": "7407672",
                "url": "https://images.start.gg/images/tournament/713228/image-42c5d7a4e9421fabd9655ca9fdc164f0.png?ehk=OY3NPvpYegfTP%2BSMbP9fSTVXHBlQt9rj7GRe39Ww3To%3D&ehkOptimized=nbnODE%2BR1BnNU19fH1s0PPHVtj%2F78uGSIlJePEwmAYs%3D",
                "type": "profile"
            },
            {
                "id": "7407673",
                "url": "https://images.start.gg/images/tournament/713228/image-784a7d105a03d0e280adb038ba142922.jpg?ehk=R8A7h9co%2F03t6AslQScnYMXtKHxYq%2B%2FqGaBOi5dQ9AU%3D&ehkOptimized=YTtIGA0dJUYbCVHTV77bH9p5vxVU2x9KcmFLISGNoCQ%3D",
                "type": "banner"
            }
        ],
        "tournament_multievent": false,
        "tournament_venueName": null,
        "tournament_venueAddress": "Julio Zegers 4223, 7790728 Santiago, \u00d1u\u00f1oa, Regi\u00f3n Metropolitana, Chile",
        "tournament_addrState": "Regi\u00f3n Metropolitana",
        "tweet_id": "1838745579121246569",
        "postedRegistrationClosing": true,
        "postedPhaseResultIds": [
            2626346
        ],
        "postedStarting": true
    },
    "1213013": {
        "id": 1213013,
        "name": "Smash Ultimate Singles",
        "isOnline": false,
        "state": "CREATED",
        "numEntrants": 4,
        "videogame": {
            "id": 1386
        },
        "startAt": 1727476200,
        "phaseGroups": [
            {
                "id": 2608724,
                "phase": {
                    "id": 1759224,
                    "name": "Bracket"
                },
                "progressionsOut": null
            }
        ],
        "tournament": "Nage House #11",
        "tournament_id": 707870,
        "city": "Temuco",
        "url": "https://start.gg/tournament/nage-house-11/event/smash-ultimate-singles",
        "streams": null,
        "timezone": "America/Santiago",
        "tournament_startAt": 1727476200,
        "tournament_endAt": 1727487900,
        "tournament_registrationClosesAt": 1727475300,
        "images": [
            {
                "id": "7353071",
                "url": "https://images.start.gg/images/tournament/707870/image-dc0fe1c62a2531c9d39314282290dea3.png?ehk=81ui5jMMy4BzGXok17Lg8GpJaeUSOjwjNODegnoL%2Buo%3D&ehkOptimized=2wagSoJUzbJSXc8KR4q1pcc7oMbqNha%2Bk5mwhKJ1gTs%3D",
                "type": "profile"
            },
            {
                "id": "7353072",
                "url": "https://images.start.gg/images/tournament/707870/image-f292ee717388abccbecffd07099815d0.jpg?ehk=larv6Y%2FboMbH5H3%2BLhbmaY3CXD%2F18SuXbJ7RvmDeHlA%3D&ehkOptimized=K0FpnzUHV%2BPqgHW195ZGpanbTHcs86E02nUwg3IyAiQ%3D",
                "type": "banner"
            }
        ],
        "tournament_multievent": false,
        "tournament_venueName": null,
        "tournament_venueAddress": "Los Talletes 1365, 01365 Temuco, Araucan\u00eda, Chile",
        "tournament_addrState": "Araucan\u00eda",
        "tweet_id": "1838926694251475352",
        "postedRegistrationClosing": true
    },
    "1222659": {
        "id": 1222659,
        "name": "Smash Bros Utimate Singles",
        "isOnline": false,
        "state": "CREATED",
        "numEntrants": 21,
        "videogame": {
            "id": 1386
        },
        "startAt": 1728230400,
        "phaseGroups": [
            {
                "id": 2625151,
                "phase": {
                    "id": 1771669,
                    "name": "Bracket"
                },
                "progressionsOut": null
            }
        ],
        "tournament": "Mk~Burgers #1",
        "tournament_id": 712821,
        "city": "\u00d1uble",
        "url": "https://start.gg/tournament/mk-burgers-1/event/smash-bros-utimate-singles",
        "streams": null,
        "timezone": "America/Santiago",
        "tournament_startAt": 1728225000,
        "tournament_endAt": 1728255600,
        "tournament_registrationClosesAt": 1728230400,
        "images": [
            {
                "id": "7403825",
                "url": "https://images.start.gg/images/tournament/712821/image-503581c1bed17bffc5d0c06291239308.png?ehk=P3uht87l7NLc28DC5zjhIIU%2FfnCDCQ%2BN7%2BVsCVGafVM%3D&ehkOptimized=RHITPxXAY4jCw6cmGKj4Zve0gnuLGP9o6Fd3zSbRUfY%3D",
                "type": "profile"
            },
            {
                "id": "7404105",
                "url": "https://images.start.gg/images/tournament/712821/image-7151fe5a1319328a2dcb6aef5f99f143.jpg?ehk=5KhFCCfqnGdczWCS6IGb%2FTdRIrYWHpB%2Bsw0xHYOT%2FjI%3D&ehkOptimized=WvWHvYAZZ4DDFxTs%2BJBkybZYlmZSjl1XTX7oh4KOZ%2Bc%3D",
                "type": "banner"
            }
        ],
        "tournament_multievent": false,
        "tournament_venueName": null,
        "tournament_venueAddress": "Arauco 1112, 3801740 \u00d1uble, Chill\u00e1n, \u00d1uble, Chile",
        "tournament_addrState": "\u00d1uble",
        "tweet_id": "1839432534033105104"
    },
    "1225910": {
        "id": 1225910,
        "name": "El Galleon Rancaguino #10 - Doubles",
        "isOnline": false,
        "state": "CREATED",
        "numEntrants": 0,
        "videogame": {
            "id": 1386
        },
        "startAt": 1728140400,
        "phaseGroups": [
            {
                "id": 2630508,
                "phase": {
                    "id": 1775953,
                    "name": "Bracket"
                },
                "progressionsOut": null
            }
        ],
        "tournament": "El Galleon Rancaguino #10 (GameDev Fest)",
        "tournament_id": 714477,
        "city": "Rancagua",
        "url": "https://start.gg/tournament/el-galleon-rancaguino-10-gamedev-fest/event/el-galleon-rancaguino-10-doubles",
        "streams": null,
        "timezone": "America/Santiago",
        "tournament_startAt": 1728140400,
        "tournament_endAt": 1728702000,
        "tournament_registrationClosesAt": 1728702000,
        "images": [
            {
                "id": "7422461",
                "url": "https://images.start.gg/images/tournament/714477/image-e7663b0a5053f846e1879f6ad51795c5.png?ehk=m10q5hvRF5XQlG530S7K2JxyVdjkMz5gf83e9cDViJE%3D&ehkOptimized=wLgU0HlGc9C1F3aOzicEh%2BJsCHOL%2Bma1YH4Ba6iSJw0%3D",
                "type": "profile"
            },
            {
                "id": "7422486",
                "url": "https://images.start.gg/images/tournament/714477/image-a3e7f05d713c9c6f3519d034859f0060.png?ehk=gkmIbqU4zDI2lDtMAu8%2BbqNgsK8A6JB9N5rQM88sZ1g%3D&ehkOptimized=pRY4SMMtdYUF62MrnEkRa7InCkvtixkWu5HLGvtdpXI%3D",
                "type": "banner"
            }
        ],
        "tournament_multievent": true,
        "tournament_venueName": null,
        "tournament_venueAddress": "Cachapoal 90, Rancagua, O'Higgins, Chile",
        "tournament_addrState": "O'Higgins",
        "tweet_id": "1840149813871943886"
    },
    "1225909": {
        "id": 1225909,
        "name": "El Galleon Rancaguino #10 - Singles",
        "isOnline": false,
        "state": "CREATED",
        "numEntrants": 0,
        "videogame": {
            "id": 1386
        },
        "startAt": 1728140400,
        "phaseGroups": [
            {
                "id": 2630507,
                "phase": {
                    "id": 1775952,
                    "name": "Bracket"
                },
                "progressionsOut": null
            }
        ],
        "tournament": "El Galleon Rancaguino #10 (GameDev Fest)",
        "tournament_id": 714477,
        "city": "Rancagua",
        "url": "https://start.gg/tournament/el-galleon-rancaguino-10-gamedev-fest/event/el-galleon-rancaguino-10-singles",
        "streams": null,
        "timezone": "America/Santiago",
        "tournament_startAt": 1728140400,
        "tournament_endAt": 1728702000,
        "tournament_registrationClosesAt": 1728702000,
        "images": [
            {
                "id": "7422461",
                "url": "https://images.start.gg/images/tournament/714477/image-e7663b0a5053f846e1879f6ad51795c5.png?ehk=m10q5hvRF5XQlG530S7K2JxyVdjkMz5gf83e9cDViJE%3D&ehkOptimized=wLgU0HlGc9C1F3aOzicEh%2BJsCHOL%2Bma1YH4Ba6iSJw0%3D",
                "type": "profile"
            },
            {
                "id": "7422486",
                "url": "https://images.start.gg/images/tournament/714477/image-a3e7f05d713c9c6f3519d034859f0060.png?ehk=gkmIbqU4zDI2lDtMAu8%2BbqNgsK8A6JB9N5rQM88sZ1g%3D&ehkOptimized=pRY4SMMtdYUF62MrnEkRa7InCkvtixkWu5HLGvtdpXI%3D",
                "type": "banner"
            }
        ],
        "tournament_multievent": true,
        "tournament_venueName": null,
        "tournament_venueAddress": "Cachapoal 90, Rancagua, O'Higgins, Chile",
        "tournament_addrState": "O'Higgins",
        "tweet_id": "1840149818854830193"
    },
    "1227186": {
        "id": 1227186,
        "name": "Singles!",
        "isOnline": false,
        "state": "CREATED",
        "numEntrants": 4,
        "videogame": {
            "id": 1386
        },
        "startAt": 1727818200,
        "phaseGroups": [
            {
                "id": 2632799,
                "phase": {
                    "id": 1777658,
                    "name": "Bracket"
                },
                "progressionsOut": null
            }
        ],
        "tournament": "Coliseo Smash: IR Training #17",
        "tournament_id": 715153,
        "city": "Santiago",
        "url": "https://start.gg/tournament/coliseo-smash-ir-training-17/event/singles",
        "streams": [
            {
                "streamName": "walito_10"
            },
            {
                "streamName": "coliseosmashcos"
            }
        ],
        "timezone": "America/Santiago",
        "tournament_startAt": 1727818200,
        "tournament_endAt": 1727829000,
        "tournament_registrationClosesAt": 1727822700,
        "images": [
            {
                "id": "7428647",
                "url": "https://images.start.gg/images/tournament/715153/image-220232199e99646b09133f0622cb0252.jpg?ehk=hzJO5RuxBAyqXfYKC9Pxfn%2B3vZP%2F9Zo0V%2FWfdnFTiAM%3D&ehkOptimized=AKONQXjplTsPShJH8mKhtYhrjZ8mQrbeJUxNtmUya0E%3D",
                "type": "profile"
            },
            {
                "id": "7428648",
                "url": "https://images.start.gg/images/tournament/715153/image-64c1e6a66499a7d05e794871ffa8671f.jpg?ehk=gqeOjZAAoKjNc7XqxXlboSTjeDIC4jUu4do5dtQtTHs%3D&ehkOptimized=HerhjLqwfkoJ%2F7MEozGTHWmOLogpFwgJ3KBpITprrok%3D",
                "type": "banner"
            }
        ],
        "tournament_multievent": false,
        "tournament_venueName": null,
        "tournament_venueAddress": "Portugal 412, Santiago, Regi\u00f3n Metropolitana, Chile",
        "tournament_addrState": "Regi\u00f3n Metropolitana",
        "tweet_id": "1840806571992846664"
    },
    "1227428": {
        "id": 1227428,
        "name": "Singles",
        "isOnline": false,
        "state": "CREATED",
        "numEntrants": 9,
        "videogame": {
            "id": 1386
        },
        "startAt": 1727881200,
        "phaseGroups": [
            {
                "id": 2633135,
                "phase": {
                    "id": 1777943,
                    "name": "Bracket"
                },
                "progressionsOut": null
            }
        ],
        "tournament": "Quincenal Primavera 2024 #3",
        "tournament_id": 715257,
        "city": "Santiago",
        "url": "https://start.gg/tournament/quincenal-primavera-2024-3/event/singles",
        "streams": [
            {
                "streamName": "usmash"
            }
        ],
        "timezone": "America/Santiago",
        "tournament_startAt": 1727881200,
        "tournament_endAt": 1727895600,
        "tournament_registrationClosesAt": 1727881200,
        "images": [
            {
                "id": "7429446",
                "url": "https://images.start.gg/images/tournament/715257/image-e210e8ceecd61a9b68d7cf8f31b91fb0.jpg?ehk=81uDe98Tazs70DljcRwa%2FV8XJqO9sIh7HJBe1bn%2Bq7c%3D&ehkOptimized=zSbG68zGX%2FNUTDH77aHWeR1NaeBb7M9eeomZGkvMbOA%3D",
                "type": "profile"
            },
            {
                "id": "7429447",
                "url": "https://images.start.gg/images/tournament/715257/image-919be381f82955f553c9ce0c6c45203c.png?ehk=%2BJiim3CEAycwjI7yBM7w2lihFMD%2FoPQNlWY1DNf7PzM%3D&ehkOptimized=YXZcDAm7XWEyIuZyFJaDUDvA7ru5zsxeZQa%2F%2FED6YYI%3D",
                "type": "banner"
            }
        ],
        "tournament_multievent": false,
        "tournament_venueName": null,
        "tournament_venueAddress": "Beaucheff 850, 8370451 Santiago, Regi\u00f3n Metropolitana, Chile",
        "tournament_addrState": "Regi\u00f3n Metropolitana",
        "tweet_id": "1840851930836291884"
    },
    "1227475": {
        "id": 1227475,
        "name": "ooooooooooooooooo",
        "isOnline": true,
        "state": "CREATED",
        "numEntrants": 7,
        "videogame": {
            "id": 1386
        },
        "startAt": 1728172800,
        "phaseGroups": [
            {
                "id": 2633192,
                "phase": {
                    "id": 1777997,
                    "name": "Bracket"
                },
                "progressionsOut": null
            }
        ],
        "tournament": "Blue Badger #1",
        "tournament_id": 715279,
        "city": null,
        "url": "https://start.gg/tournament/blue-badger-1/event/ooooooooooooooooo",
        "streams": [
            {
                "streamName": "toonjorgitox99"
            }
        ],
        "timezone": "America/Santiago",
        "tournament_startAt": 1728172800,
        "tournament_endAt": 1728183600,
        "tournament_registrationClosesAt": 1728172200,
        "images": [
            {
                "id": "7429620",
                "url": "https://images.start.gg/images/tournament/715279/image-4ed170efeffa96c1ed679002f4fab47e.jpg?ehk=mHX%2FeETXkljgSOCAp3PfNq3Z7BpYGJGYz2HF9YeQ6no%3D&ehkOptimized=VqHDdFbm9ysc2iWCy%2BJIDrCfAb6KLv5K8%2BPYqMsoLV8%3D",
                "type": "profile"
            },
            {
                "id": "7429648",
                "url": "https://images.start.gg/images/tournament/715279/image-81826b5623b88a51288f05a5c129bb1c.jpg?ehk=yO6TGm0vmCUaGp11zAQvOCrsYQOdYgtjpaoYc7iHBu0%3D&ehkOptimized=5NhRCKWv0ULA8I7G4LqGx8%2B%2Bq63jgkA%2FQ0npYf%2F3LYs%3D",
                "type": "banner"
            }
        ],
        "tournament_multievent": false,
        "tournament_venueName": null,
        "tournament_venueAddress": "Chile",
        "tournament_addrState": null,
        "tweet_id": "1840904869361627434"
    }
}