{
    "1416559": {
        "id": 1416559,
        "name": "Side Event",
        "isOnline": false,
        "state": "CREATED",
        "numEntrants": 0,
        "videogame": {
            "id": 1386
        },
        "startAt": 1752940800,
        "phaseGroups": [
            {
                "id": 2959584,
                "phase": {
                    "id": 2020832,
                    "name": "Bracket"
                },
                "progressionsOut": null
            }
        ],
        "tournament": "Playcoffee League S2 #8",
        "tournament_id": 807885,
        "city": "Pucon",
        "url": "https://start.gg/tournament/playcoffee-league-s2-8/event/side-event",
        "streams": [
            {
                "streamName": "luckyinozuto"
            }
        ],
        "timezone": "America/Santiago",
        "tournament_startAt": 1752940800,
        "tournament_endAt": 1752973200,
        "tournament_registrationClosesAt": 1752897000,
        "images": [
            {
                "id": "8459102",
                "url": "https://images.start.gg/images/tournament/807885/image-addb99dd8d7f692082b72801cd26201d.jpg",
                "type": "banner"
            },
            {
                "id": "8459106",
                "url": "https://images.start.gg/images/tournament/807885/image-408989fe47e1d601165b3075f86778b9.png",
                "type": "profile"
            }
        ],
        "tournament_multievent": true,
        "tournament_venueName": null,
        "tournament_venueAddress": "Colo Colo 485, 4920474 Pucon, Puc\u00f3n, Araucan\u00eda, Chile",
        "tournament_addrState": "Araucan\u00eda",
        "tweet_id": "1943573690521735643",
        "postedRegistrationClosing": true
    },
    "1417674": {
        "id": 1417674,
        "name": "Torneo Squad Strike Random Main Invertido",
        "isOnline": false,
        "state": "ACTIVE",
        "numEntrants": 9,
        "videogame": {
            "id": 1386
        },
        "startAt": 1753027200,
        "phaseGroups": [
            {
                "id": 2961565,
                "state": 2,
                "phase": {
                    "name": "Bracket"
                },
                "progressionsOut": null,
                "standings": {
                    "pageInfo": {
                        "total": 9
                    },
                    "nodes": [
                        {
                            "placement": 2,
                            "entrant": {
                                "id": 20744483,
                                "name": "PHX | Sekai Doggo",
                                "participants": [
                                    {
                                        "user": {
                                            "authorizations": [
                                                {
                                                    "externalUsername": "SekaiDoggo"
                                                }
                                            ]
                                        },
                                        "player": {
                                            "id": 132195,
                                            "gamerTag": "Sekai Doggo"
                                        }
                                    }
                                ]
                            }
                        },
                        {
                            "placement": 3,
                            "entrant": {
                                "id": 20697964,
                                "name": "Diptox",
                                "participants": [
                                    {
                                        "user": {
                                            "authorizations": [
                                                {
                                                    "externalUsername": "Diptox44"
                                                }
                                            ]
                                        },
                                        "player": {
                                            "id": 844310,
                                            "gamerTag": "Diptox"
                                        }
                                    }
                                ]
                            }
                        },
                        {
                            "placement": 3,
                            "entrant": {
                                "id": 20738713,
                                "name": "SMB | Flame",
                                "participants": [
                                    {
                                        "user": {
                                            "authorizations": [
                                                {
                                                    "externalUsername": "MrFlame177"
                                                }
                                            ]
                                        },
                                        "player": {
                                            "id": 428407,
                                            "gamerTag": "Flame"
                                        }
                                    }
                                ]
                            }
                        },
                        {
                            "placement": 4,
                            "entrant": {
                                "id": 20748029,
                                "name": "Gs | Green",
                                "participants": [
                                    {
                                        "user": {
                                            "authorizations": null
                                        },
                                        "player": {
                                            "id": 2146968,
                                            "gamerTag": "Green"
                                        }
                                    }
                                ]
                            }
                        },
                        {
                            "placement": 5,
                            "entrant": {
                                "id": 20741943,
                                "name": "LEV/SMB | .Png!",
                                "participants": [
                                    {
                                        "user": {
                                            "authorizations": null
                                        },
                                        "player": {
                                            "id": 3592282,
                                            "gamerTag": ".Png!"
                                        }
                                    }
                                ]
                            }
                        },
                        {
                            "placement": 5,
                            "entrant": {
                                "id": 20744446,
                                "name": "Naozen | Naozen_Voidheart",
                                "participants": [
                                    {
                                        "user": {
                                            "authorizations": null
                                        },
                                        "player": {
                                            "id": 627938,
                                            "gamerTag": "Naozen_Voidheart"
                                        }
                                    }
                                ]
                            }
                        },
                        {
                            "placement": 7,
                            "entrant": {
                                "id": 20697975,
                                "name": "WLB | Maiin",
                                "participants": [
                                    {
                                        "user": {
                                            "authorizations": [
                                                {
                                                    "externalUsername": "MaiinGunner"
                                                }
                                            ]
                                        },
                                        "player": {
                                            "id": 3314124,
                                            "gamerTag": "Maiin"
                                        }
                                    }
                                ]
                            }
                        },
                        {
                            "placement": 7,
                            "entrant": {
                                "id": 20680913,
                                "name": "ElPerroWuaton",
                                "participants": [
                                    {
                                        "user": {
                                            "authorizations": null
                                        },
                                        "player": {
                                            "id": 4208597,
                                            "gamerTag": "ElPerroWuaton"
                                        }
                                    }
                                ]
                            }
                        },
                        {
                            "placement": 9,
                            "entrant": {
                                "id": 20680493,
                                "name": "DSL | Kingcrimson",
                                "participants": [
                                    {
                                        "user": {
                                            "authorizations": [
                                                {
                                                    "externalUsername": "kcrimsonssbu"
                                                }
                                            ]
                                        },
                                        "player": {
                                            "id": 1005497,
                                            "gamerTag": "Kingcrimson"
                                        }
                                    }
                                ]
                            }
                        }
                    ]
                }
            }
        ],
        "tournament": "Pelican Town - Resurection",
        "tournament_id": 808474,
        "city": "Puerto Montt",
        "url": "https://start.gg/tournament/pelican-town-resurection/event/torneo-squad-strike-random-main-invertido",
        "streams": [
            {
                "streamName": "sekaidoggo"
            },
            {
                "streamName": "magoea"
            }
        ],
        "timezone": "America/Santiago",
        "tournament_startAt": 1753027200,
        "tournament_endAt": 1753048800,
        "tournament_registrationClosesAt": 1753034400,
        "images": [
            {
                "id": "8466516",
                "url": "https://images.start.gg/images/tournament/808474/image-a3be66c8857a2bf8c22df596763a04be.png",
                "type": "profile"
            },
            {
                "id": "8466517",
                "url": "https://images.start.gg/images/tournament/808474/image-f1de8cba9b6fc4c6a7e2cce0a7182420.png",
                "type": "banner"
            }
        ],
        "tournament_multievent": true,
        "tournament_venueName": null,
        "tournament_venueAddress": "Calle Nueva Ote. 4 5513, Puerto Montt, Los Lagos, Chile",
        "tournament_addrState": "Los Lagos",
        "tweet_id": "1944442005238542784",
        "postedRegistrationClosing": true,
        "postedPhaseResultIds": [],
        "postedStarting": true
    },
    "1419206": {
        "id": 1419206,
        "name": "Duplas Only DK + barra smash",
        "isOnline": false,
        "state": "CREATED",
        "numEntrants": 0,
        "videogame": {
            "id": 1386
        },
        "startAt": 1753041600,
        "phaseGroups": [
            {
                "id": 2963793,
                "phase": {
                    "id": 2024170,
                    "name": "Bracket"
                },
                "progressionsOut": null
            }
        ],
        "tournament": "Mango Exprezz Zeriez #11: \u00a1Comete un mango entonce'!",
        "tournament_id": 809191,
        "city": "San Fernando",
        "url": "https://start.gg/tournament/mango-exprezz-zeriez-11-comete-un-mango-entonce/event/duplas-only-dk-barra-smash",
        "streams": null,
        "timezone": "America/Santiago",
        "tournament_startAt": 1753030800,
        "tournament_endAt": 1753057800,
        "tournament_registrationClosesAt": 1753057800,
        "images": [
            {
                "id": "8473024",
                "url": "https://images.start.gg/images/tournament/809191/image-b7bf40e7170984ce7a9389c1bcbac5bd.png",
                "type": "profile"
            }
        ],
        "tournament_multievent": true,
        "tournament_venueName": null,
        "tournament_venueAddress": "Lautaro 101, 3070000 San Fernando, O'Higgins, Chile",
        "tournament_addrState": "O'Higgins",
        "tweet_id": "1945181930808361221",
        "postedRegistrationClosing": true
    },
    "1421040": {
        "id": 1421040,
        "name": "Low Tier",
        "isOnline": false,
        "state": "CREATED",
        "numEntrants": 0,
        "videogame": {
            "id": 1386
        },
        "startAt": 1753641000,
        "phaseGroups": [
            {
                "id": 2966865,
                "phase": {
                    "id": 2026532,
                    "name": "Bracket"
                },
                "progressionsOut": null
            }
        ],
        "tournament": "Venus: 1th Smash Cabrero Anniversary",
        "tournament_id": 810030,
        "city": "Cabrero",
        "url": "https://start.gg/tournament/venus-1th-smash-cabrero-anniversary/event/low-tier",
        "streams": null,
        "timezone": "America/Santiago",
        "tournament_startAt": 1753641000,
        "tournament_endAt": 1753657200,
        "tournament_registrationClosesAt": 1753657200,
        "images": [
            {
                "id": "8483456",
                "url": "https://images.start.gg/images/tournament/810030/image-b838a1d28598e2d271e462d129300203.jpg",
                "type": "profile"
            },
            {
                "id": "8483465",
                "url": "https://images.start.gg/images/tournament/810030/image-7849f5a47226d1039501df9828d0a391.jpg",
                "type": "banner"
            }
        ],
        "tournament_multievent": true,
        "tournament_venueName": null,
        "tournament_venueAddress": "Cabrero, Bio Bio, Chile",
        "tournament_addrState": "Bio Bio",
        "tweet_id": "1946254095292985713"
    },
    "1421036": {
        "id": 1421036,
        "name": "Ultimate Singles",
        "isOnline": false,
        "state": "CREATED",
        "numEntrants": 7,
        "videogame": {
            "id": 1386
        },
        "startAt": 1753641000,
        "phaseGroups": [
            {
                "id": 2966859,
                "phase": {
                    "id": 2026527,
                    "name": "Bracket"
                },
                "progressionsOut": null
            }
        ],
        "tournament": "Venus: 1th Smash Cabrero Anniversary",
        "tournament_id": 810030,
        "city": "Cabrero",
        "url": "https://start.gg/tournament/venus-1th-smash-cabrero-anniversary/event/ultimate-singles",
        "streams": null,
        "timezone": "America/Santiago",
        "tournament_startAt": 1753641000,
        "tournament_endAt": 1753657200,
        "tournament_registrationClosesAt": 1753657200,
        "images": [
            {
                "id": "8483456",
                "url": "https://images.start.gg/images/tournament/810030/image-b838a1d28598e2d271e462d129300203.jpg",
                "type": "profile"
            },
            {
                "id": "8483465",
                "url": "https://images.start.gg/images/tournament/810030/image-7849f5a47226d1039501df9828d0a391.jpg",
                "type": "banner"
            }
        ],
        "tournament_multievent": true,
        "tournament_venueName": null,
        "tournament_venueAddress": "Cabrero, Bio Bio, Chile",
        "tournament_addrState": "Bio Bio",
        "tweet_id": "1946254100263276849"
    },
    "1421674": {
        "id": 1421674,
        "name": "Octo Canyon #7",
        "isOnline": false,
        "state": "CREATED",
        "numEntrants": 3,
        "videogame": {
            "id": 1386
        },
        "startAt": 1752962400,
        "phaseGroups": [
            {
                "id": 2968122,
                "phase": {
                    "id": 2027407,
                    "name": "Bracket"
                },
                "progressionsOut": null
            }
        ],
        "tournament": "Pay to win #1",
        "tournament_id": 810321,
        "city": "Antofagasta",
        "url": "https://start.gg/tournament/pay-to-win-1-1/event/octo-canyon-7",
        "streams": null,
        "timezone": "America/Santiago",
        "tournament_startAt": 1752962400,
        "tournament_endAt": 1752976800,
        "tournament_registrationClosesAt": 1752976800,
        "images": [
            {
                "id": "8487245",
                "url": "https://images.start.gg/images/tournament/810321/image-ea5be08e5bcc5c7c44c6fdfadd4e544c.jpg",
                "type": "profile"
            }
        ],
        "tournament_multievent": false,
        "tournament_venueName": null,
        "tournament_venueAddress": "Av. Pedro Aguirre Cerda 11092, 1267093 Antofagasta, Chile",
        "tournament_addrState": "Antofagasta",
        "tweet_id": "1946684293918388621",
        "postedRegistrationClosing": true
    },
    "1420195": {
        "id": 1420195,
        "name": "Ultimate Singles",
        "isOnline": false,
        "state": "CREATED",
        "numEntrants": 13,
        "videogame": {
            "id": 1386
        },
        "startAt": 1753547400,
        "phaseGroups": [
            {
                "id": 2965486,
                "phase": {
                    "id": 2025442,
                    "name": "Bracket"
                },
                "progressionsOut": [
                    {
                        "id": 12469155
                    },
                    {
                        "id": 12469156
                    },
                    {
                        "id": 12469157
                    },
                    {
                        "id": 12469158
                    },
                    {
                        "id": 12469159
                    },
                    {
                        "id": 12469160
                    },
                    {
                        "id": 12469161
                    },
                    {
                        "id": 12469162
                    }
                ]
            },
            {
                "id": 2965487,
                "phase": {
                    "id": 2025443,
                    "name": "Top 8"
                },
                "progressionsOut": null
            },
            {
                "id": 2965488,
                "phase": {
                    "id": 2025444,
                    "name": "Resurrection"
                },
                "progressionsOut": null
            }
        ],
        "tournament": "\ud83c\udf54Gourmet Galaxy Second\ud83e\ude90",
        "tournament_id": 809641,
        "city": "Rancagua",
        "url": "https://start.gg/tournament/gourmet-galaxy-second/event/ultimate-singles",
        "streams": [
            {
                "streamName": "smashfamily"
            }
        ],
        "timezone": "America/Santiago",
        "tournament_startAt": 1753547400,
        "tournament_endAt": 1753574400,
        "tournament_registrationClosesAt": 1753459260,
        "images": [
            {
                "id": "8484913",
                "url": "https://images.start.gg/images/tournament/809641/image-897a0b45bc3787c0e379798d767531a5.png",
                "type": "profile"
            },
            {
                "id": "8484927",
                "url": "https://images.start.gg/images/tournament/809641/image-232ef1a254f5421ebbef2fe4c1d6f607.png",
                "type": "banner"
            }
        ],
        "tournament_multievent": false,
        "tournament_venueName": null,
        "tournament_venueAddress": "San Mart\u00edn 145, 2820000 Rancagua, O'Higgins, Chile",
        "tournament_addrState": "O'Higgins",
        "tweet_id": "1947099665658171794"
    },
    "1355003": {
        "id": 1355003,
        "name": "Smash Ultimate Singles",
        "isOnline": false,
        "state": "CREATED",
        "numEntrants": 4,
        "videogame": {
            "id": 1386
        },
        "startAt": 1753398000,
        "phaseGroups": [
            {
                "id": 2850788,
                "phase": {
                    "id": 1941097,
                    "name": "Bracket"
                },
                "progressionsOut": null
            }
        ],
        "tournament": "Nage House #20",
        "tournament_id": 777891,
        "city": "Temuco",
        "url": "https://start.gg/tournament/nage-house-20/event/smash-ultimate-singles",
        "streams": null,
        "timezone": "America/Santiago",
        "tournament_startAt": 1753398000,
        "tournament_endAt": 1753408800,
        "tournament_registrationClosesAt": 1753398000,
        "images": [
            {
                "id": "8095077",
                "url": "https://images.start.gg/images/tournament/777891/image-11c6587737ee6e9b5727f3d53a79e2b4.png",
                "type": "profile"
            },
            {
                "id": "8095079",
                "url": "https://images.start.gg/images/tournament/777891/image-7143b0192fabc2d9ec044befb68d5ae0.jpg",
                "type": "banner"
            }
        ],
        "tournament_multievent": false,
        "tournament_venueName": null,
        "tournament_venueAddress": "Los Talletes 1365, 01365 Temuco, Araucan\u00eda, Chile",
        "tournament_addrState": "Araucan\u00eda",
        "tweet_id": "1947507238521770343"
    },
    "1423199": {
        "id": 1423199,
        "name": "Ultimate Singles",
        "isOnline": false,
        "state": "CREATED",
        "numEntrants": 4,
        "videogame": {
            "id": 1386
        },
        "startAt": 1753210800,
        "phaseGroups": [
            {
                "id": 2971655,
                "phase": {
                    "id": 2029430,
                    "name": "Bracket"
                },
                "progressionsOut": null
            }
        ],
        "tournament": "Lion Match",
        "tournament_id": 811123,
        "city": "Los Angeles",
        "url": "https://start.gg/tournament/lion-match",
        "streams": null,
        "timezone": "America/Santiago",
        "tournament_startAt": 1753210800,
        "tournament_endAt": 1753223400,
        "tournament_registrationClosesAt": 1753223400,
        "images": [
            {
                "id": "8495334",
                "url": "https://images.start.gg/images/tournament/811123/image-d970bac4ab7c8d1eaec86f4c7c39c728.jpg",
                "type": "profile"
            }
        ],
        "tournament_multievent": false,
        "tournament_venueName": null,
        "tournament_venueAddress": "Los Angeles, Los \u00c1ngeles, B\u00edo B\u00edo, Chile",
        "tournament_addrState": "B\u00edo B\u00edo",
        "tweet_id": "1947522285499269365"
    }
}